st_keyup_react/__init__.py
st_keyup_react/frontend/build/asset-manifest.json
st_keyup_react/frontend/build/index.html
st_keyup_react/frontend/build/static/css/main.5657db29.css
st_keyup_react/frontend/build/static/css/main.5657db29.css.map
st_keyup_react/frontend/build/static/js/main.429a888e.js
st_keyup_react/frontend/build/static/js/main.429a888e.js.LICENSE.txt
st_keyup_react/frontend/build/static/js/main.429a888e.js.map
streamlit_keyup_react-0.1.0.dist-info/LICENSE
streamlit_keyup_react-0.1.0.dist-info/METADATA
streamlit_keyup_react-0.1.0.dist-info/WHEEL
streamlit_keyup_react-0.1.0.dist-info/top_level.txt
streamlit_keyup_react-0.1.0.dist-info/RECORD
