Metadata-Version: 2.1
Name: streamlit-keyup-react
Version: 0.1.0
Summary: Text input that renders on keyup
Home-page: https://github.com/animebing/streamlit-keyup-react
Author: Yanbing Dong
Author-email: yanbing_dong@hotmail.com
Requires-Python: >=3.7
License-File: LICENSE
Requires-Dist: streamlit >=1.2
